EasyPySpin/__init__.py
EasyPySpin/command_line.py
EasyPySpin/multiplevideocapture.py
EasyPySpin/synchronizedvideocapture.py
EasyPySpin/utils.py
EasyPySpin/videocapture.py
EasyPySpin/videocaptureex.py
EasyPySpin-2.0.1.dist-info/LICENSE
EasyPySpin-2.0.1.dist-info/METADATA
EasyPySpin-2.0.1.dist-info/WHEEL
EasyPySpin-2.0.1.dist-info/entry_points.txt
EasyPySpin-2.0.1.dist-info/top_level.txt
EasyPySpin-2.0.1.dist-info/RECORD
