Metadata-Version: 2.1
Name: EasyPySpin
Version: 2.0.1
Summary: cv2.VideoCapture like wrapper for FLIR Spinnaker SDK
Home-page: https://github.com/elerac/EasyPySpin
Author: Ryota Maeda
Author-email: maeda.ryota.elerac@gmail.com
License: MIT
Platform: UNKNOWN
